Metadata-Version: 2.0
Name: django-tenant-schemas-ap
Version: 0.1.1
Summary: Tenant support for Django using PostgreSQL schemas.
Home-page: https://github.com/bcarneiro/django-tenant-schemas
Author: Bernardo Pires Carneiro
Author-email: carneiro.be@gmail.com
License: MIT
Platform: UNKNOWN
Classifier: License :: OSI Approved :: MIT License
Classifier: Framework :: Django
Classifier: Programming Language :: Python
Requires-Dist: Django (>=1.6.0)
Requires-Dist: psycopg2
